README.md
setup.cfg
setup.py
test/test_accepted_payment.py
test/test_access_token_response.py
test/test_access_token_validation_request.py
test/test_auth_response.py
test/test_auto_top_up_config.py
test/test_challenge.py
test/test_company.py
test/test_company2.py
test/test_company_response.py
test/test_company_v1.py
test/test_countries_api.py
test/test_create_funding_account_request.py
test/test_create_individual.py
test/test_create_individual2.py
test/test_create_individual2_name.py
test/test_create_payee.py
test/test_create_payee2.py
test/test_create_payee_address.py
test/test_create_payee_address2.py
test/test_create_payees_csv_request.py
test/test_create_payees_csv_request2.py
test/test_create_payees_csv_response.py
test/test_create_payees_csv_response2.py
test/test_create_payees_csv_response_rejected_csv_rows.py
test/test_create_payees_request.py
test/test_create_payees_request2.py
test/test_create_payment_channel.py
test/test_create_payment_channel2.py
test/test_create_payor_link_request.py
test/test_create_payout_request.py
test/test_currencies_api.py
test/test_currency_type.py
test/test_error.py
test/test_error_response.py
test/test_failed_submission.py
test/test_failed_submission2.py
test/test_funding_account_response.py
test/test_funding_audit.py
test/test_funding_event.py
test/test_funding_event_type.py
test/test_funding_manager_api.py
test/test_funding_manager_private_api.py
test/test_funding_payor_status_audit_response.py
test/test_funding_request_v1.py
test/test_funding_request_v2.py
test/test_fx_summary_v3.py
test/test_fx_summary_v4.py
test/test_get_fundings_response.py
test/test_get_fundings_response_all_of.py
test/test_get_payments_for_payout_response_v3.py
test/test_get_payments_for_payout_response_v3_page.py
test/test_get_payments_for_payout_response_v3_summary.py
test/test_get_payments_for_payout_response_v4.py
test/test_get_payments_for_payout_response_v4_summary.py
test/test_get_payout_api.py
test/test_get_payout_statistics.py
velo_python.egg-info/PKG-INFO
velo_python.egg-info/SOURCES.txt
velo_python.egg-info/dependency_links.txt
velo_python.egg-info/requires.txt
velo_python.egg-info/top_level.txt