Metadata-Version: 1.0
Name: velo-python
Version: 2.20.118
Summary: Velo Payments APIs
Home-page: https://github.com/velopaymentsapi/velo-python
Author: OpenAPI Generator community
Author-email: team@openapitools.org
License: Apache License 2.0
Keywords: OpenAPI,OpenAPI-Generator,Velo Payments APIs
Platform: UNKNOWN
